visgeo_lms/__init__.py
visgeo_lms/__main__.py
visgeo_lms-0.1.0.dist-info/LICENSE
visgeo_lms-0.1.0.dist-info/METADATA
visgeo_lms-0.1.0.dist-info/WHEEL
visgeo_lms-0.1.0.dist-info/entry_points.txt
visgeo_lms-0.1.0.dist-info/top_level.txt
visgeo_lms-0.1.0.dist-info/RECORD
