Metadata-Version: 2.1
Name: visgeo_lms
Version: 0.1.0
Summary: An interactive bivariate cartogram mapping tool with LLM support
Author: Wang Zhe，Zhang Zuo，Zhang Rui，Jiang Yukun
Author-email: wangzhecnc@163.com
Requires-Python: >=3.8
License-File: LICENSE
Requires-Dist: PyQt5
Requires-Dist: geopandas
Requires-Dist: folium
Requires-Dist: jenkspy
Requires-Dist: openai
Requires-Dist: numpy
